octo_bots_python/__init__.py
octo_bots_python/background_job.py
octo_bots_python/bot.py
octo_bots_python/bots_client.py
octo_bots_python/bots_config.py
octo_bots_python/bots_executor.py
octo_bots_python/bots_flask_manager.py
octo_bots_python/bots_serverless_manager.py
octo_bots_python/bots_settings.py
octo_bots_python/clients/__init__.py
octo_bots_python/clients/checkmarx_client.py
octo_bots_python/clients/github_client.py
octo_bots_python/common/__init__.py
octo_bots_python/common/logger.py
octo_bots_python/config/flask/bots_manager_config.yml
octo_bots_python/config/flask/bots/github_branch_bot.yml
octo_bots_python/config/flask/bots/github_checkmarx_bot.yml
octo_bots_python/config/flask/bots/github_clang_bot.yml
octo_bots_python/config/flask/bots/github_cppcheck_bot.yml
octo_bots_python/config/flask/bots/github_pr_bot.yml
octo_bots_python/config/flask/jobs/github_stale_job.yml
octo_bots_python/config/serverless/bots_manager_config.yml
octo_bots_python/data/octo-bots.service
octo_bots_python/data/octo_bots_install_service.sh
octo_bots_python/filters/__init__.py
octo_bots_python/filters/filter.py
octo_bots_python/filters/filters_loader.py
octo_bots_python/filters/github/__init__.py
octo_bots_python/filters/github/branch_filter.py
octo_bots_python/filters/github/events_filter.py
octo_bots_python/filters/github/file_filter.py
octo_bots_python/filters/github/repo_filter.py
octo_bots_python/operations/__init__.py
octo_bots_python/operations/operation.py
octo_bots_python/operations/operations_loader.py
octo_bots_python/operations/github/__init__.py
octo_bots_python/operations/github/branch_deleted_checkmarx_cleanup_operation.py
octo_bots_python/operations/github/clang_format_validator_operation.py
octo_bots_python/operations/github/close_stale_operation.py
octo_bots_python/operations/github/pull_request_checkmarx_operation.py
octo_bots_python/operations/github/pull_request_cppcheck_operation.py
octo_bots_python/operations/github/pull_request_forbidden_files_operation.py
octo_bots_python-1.0.0.dist-info/LICENSE.txt
octo_bots_python-1.0.0.dist-info/METADATA
octo_bots_python-1.0.0.dist-info/README.md
octo_bots_python-1.0.0.dist-info/WHEEL
octo_bots_python-1.0.0.dist-info/entry_points.txt
octo_bots_python-1.0.0.dist-info/top_level.txt
octo_bots_python-1.0.0.dist-info/RECORD
