Metadata-Version: 2.1
Name: octo-bots-python
Version: 1.0.0
Summary: Octo bots management for github checks / bots
Home-page: https://github.com/ofiriluz/octo-bots-python
Author: Ofir Iluz
Author-email: iluzofir@gmail.com
License: MIT
Classifier: Intended Audience :: Developers
Classifier: Natural Language :: English
Classifier: Programming Language :: Python
Classifier: Programming Language :: Python :: 3.8
Classifier: Programming Language :: Python :: 3.9
Classifier: Programming Language :: Python :: 3.10
Requires-Python: >= 3.8
License-File: LICENSE.txt
License-File: README.md
Requires-Dist: PyGithub
Requires-Dist: GitPython
Requires-Dist: colorama
Requires-Dist: flask
Requires-Dist: dateparser
Requires-Dist: CheckmarxPythonSDK
Requires-Dist: requests
Requires-Dist: pyyaml
Requires-Dist: cryptography
Requires-Dist: pydantic
